LICENSE
README.md
crosspm/__init__.py
crosspm/__main__.py
crosspm/cmakepm.cmake
crosspm/config.py
crosspm/cpm.py
crosspm/crosspm.cmake
crosspm/adapters/__init__.py
crosspm/adapters/artifactoryaql.py
crosspm/adapters/artifactoryaql2.py
crosspm/adapters/common.py
crosspm/adapters/files.py
crosspm/contracts/__init__.py
crosspm/contracts/bundle.py
crosspm/contracts/contract.py
crosspm/contracts/package.py
crosspm/contracts/package_version.py
crosspm/helpers/__init__.py
crosspm/helpers/config.py
crosspm/helpers/downloader.py
crosspm/helpers/exceptions.py
crosspm/helpers/locker.py
crosspm/helpers/locker2.py
crosspm/helpers/package.py
crosspm/helpers/parser.py
crosspm/helpers/parser2.py
crosspm/helpers/promoter.py
crosspm/helpers/source.py
crosspm/helpers/usedby.py
crosspm/template/__init__.py
crosspm/template/all_yaml.j2
crosspm/template/gus.j2
crosspm2-2.0.1.114.dist-info/LICENSE
crosspm2-2.0.1.114.dist-info/METADATA
crosspm2-2.0.1.114.dist-info/WHEEL
crosspm2-2.0.1.114.dist-info/entry_points.txt
crosspm2-2.0.1.114.dist-info/top_level.txt
crosspm2-2.0.1.114.dist-info/RECORD
