Metadata-Version: 2.1
Name: crosspm2
Version: 2.0.1.114
Summary: Cross Package Manager 2
Home-page: https://devopshq.github.io/crosspm2/
Author: Timut Gilmullin
Author-email: tim55667757@gmail.com
License: MIT
Download-URL: https://github.com/devopshq/crosspm2.git
Keywords: development,dependency,requirements,manager,versioning,packet
Platform: UNKNOWN
Classifier: Development Status :: 5 - Production/Stable
Classifier: Environment :: Console
Classifier: Intended Audience :: Developers
Classifier: Topic :: Software Development :: Build Tools
Classifier: License :: OSI Approved :: MIT License
Classifier: Natural Language :: English
Classifier: Programming Language :: Python :: 3
License-File: LICENSE
Requires-Dist: urllib3 (==1.24.3)
Requires-Dist: docopt (==0.6.2)
Requires-Dist: dohq-common
Requires-Dist: patool (==1.12)
Requires-Dist: pyunpack (==0.1.2)
Requires-Dist: addict (==2.2.1)
Requires-Dist: packaging (>=20.4)
Requires-Dist: parse (>=1.15.0)
Requires-Dist: tabulate (>=0.8.7)
Requires-Dist: ordered-set (>=4.0.2)
Requires-Dist: wcmatch
Requires-Dist: requests (<2.22) ; python_version < "3.5"
Requires-Dist: PyYAML (==5.1.2) ; python_version < "3.5"
Requires-Dist: dohq-artifactory (==0.4.112) ; python_version < "3.5"
Requires-Dist: Jinja2 (<2.11) ; python_version < "3.5"
Requires-Dist: requests (>=2.22) ; python_version >= "3.5"
Requires-Dist: PyYAML (>=5.2) ; python_version >= "3.5"
Requires-Dist: dohq-artifactory (>=0.7.377) ; python_version >= "3.5"
Requires-Dist: Jinja2 (>=2.11) ; python_version >= "3.5"
